[1,["fcg4sWeIdHaqXOAibF328a","d3pTkZ/cpHkLNvoiTsH5h0","ceug+edxBI7oSvuckGI6eI"],["_textureSetter","返回","返回_7bda30ee-02e9-426f-bd7d-ab2a230f8eac"],["cc.SpriteFrame",["cc.SpriteAtlas",["_name","_spriteFrames"],2,11]],[[1,0,1,2]],[[[[0,"返回.plist",[{},"返回",6,0,"返回_7bda30ee-02e9-426f-bd7d-ab2a230f8eac",6,1]]],0,0,[0,0],[1,2],[1,2]],[[{"name":"返回_7bda30ee-02e9-426f-bd7d-ab2a230f8eac","rect":[0,0,133,147],"offset":[0,0],"originalSize":[133,147],"capInsets":[0,0,0,0]}],[0],0,[0],[0],[0]],[[{"name":"返回","rect":[0,0,133,147],"offset":[0,0],"originalSize":[133,147],"capInsets":[0,0,0,0]}],[0],0,[0],[0],[0]]]]