[1,0,0,[["cc.JsonAsset",["_name","json"],1]],[[0,0,1,3]],[[0,"dressClassData",[{"index":0,"imageName":"人体","spineType":0,"isClear":false,"isColor":false},{"index":56,"imageName":"diy涂色","spineType":0,"isClear":false,"isColor":false},{"index":1,"imageName":"肤色","spineType":0,"isClear":false,"isColor":true},{"index":2,"imageName":"前发","spineType":0,"isClear":false,"isColor":true,"isNew":1},{"index":3,"imageName":"后发","spineType":0,"isClear":false,"isColor":true,"isNew":1},{"index":8,"imageName":"裙子","spineType":0,"isClear":false,"isColor":false,"isNew":1},{"index":4,"imageName":"眼睛","spineType":0,"isClear":false,"isColor":true},{"index":5,"imageName":"眉毛","spineType":0,"isClear":false,"isColor":true},{"index":6,"imageName":"嘴巴","spineType":0,"isClear":false,"isColor":false},{"index":7,"imageName":"面部腮红","spineType":0,"isClear":true,"isColor":false},{"index":19,"imageName":"鼻子","spineType":0,"isClear":false,"isColor":false},{"index":9,"imageName":"上装","spineType":0,"isClear":false,"isColor":false,"isNew":1},{"index":10,"imageName":"下装","spineType":0,"isClear":false,"isColor":false,"isNew":1},{"index":11,"imageName":"袜子","spineType":0,"isClear":true,"isColor":false,"isNew":1},{"index":12,"imageName":"鞋子","spineType":0,"isClear":true,"isColor":false,"isNew":1},{"index":13,"imageName":"头饰","spineType":0,"isClear":true,"isColor":false,"isNew":1},{"index":14,"imageName":"眼镜选择","spineType":0,"isClear":true,"isColor":false,"isNew":1},{"index":15,"imageName":"项链","spineType":0,"isClear":true,"isColor":false,"isNew":1},{"index":16,"imageName":"手饰","spineType":0,"isClear":true,"isColor":false,"isNew":1},{"index":17,"imageName":"耳环","spineType":0,"isClear":true,"isColor":false,"isNew":1},{"index":21,"imageName":"手持物","spineType":0,"isClear":true,"isColor":false},{"index":54,"imageName":"肤色","spineType":1,"isClear":false,"isColor":true},{"index":26,"imageName":"发型_kid","spineType":1,"isClear":false,"isColor":true},{"index":27,"imageName":"眉毛","spineType":1,"isClear":false,"isColor":true},{"index":28,"imageName":"眼睛","spineType":1,"isClear":false,"isColor":true},{"index":30,"imageName":"嘴巴","spineType":1,"isClear":false,"isColor":false},{"index":31,"imageName":"面部腮红","spineType":1,"isClear":true,"isColor":false},{"index":32,"imageName":"裙子","spineType":1,"isClear":false,"isColor":false},{"index":33,"imageName":"上装_kid","spineType":1,"isClear":false,"isColor":false},{"index":34,"imageName":"下装_kid","spineType":1,"isClear":false,"isColor":false},{"index":35,"imageName":"袜子","spineType":1,"isClear":true,"isColor":false},{"index":36,"imageName":"鞋子","spineType":1,"isClear":true,"isColor":false},{"index":37,"imageName":"连体衣_kid","spineType":1,"isClear":false,"isColor":false},{"index":46,"imageName":"小体型面饰","spineType":1,"isClear":true,"isColor":false},{"index":49,"imageName":"头饰","spineType":1,"isClear":true,"isColor":false},{"index":55,"imageName":"肤色","spineType":2,"isClear":false,"isColor":true},{"index":38,"imageName":"眼睛","spineType":2,"isClear":false,"isColor":true},{"index":39,"imageName":"面部腮红","spineType":2,"isClear":true,"isColor":false},{"index":40,"imageName":"嘴巴","spineType":2,"isClear":false,"isColor":false},{"index":41,"imageName":"小体型面饰","spineType":2,"isClear":true,"isColor":false},{"index":42,"imageName":"眉毛","spineType":2,"isClear":false,"isColor":true},{"index":44,"imageName":"发型_baby","spineType":2,"isClear":false,"isColor":true},{"index":45,"imageName":"襁褓_baby","spineType":2,"isClear":false,"isColor":false},{"index":1,"imageName":"M肤色","isClear":false,"isColor":false},{"index":2,"imageName":"M翅膀","isClear":true,"isColor":false,"isNew":1},{"index":3,"imageName":"M犄角","isClear":true,"isColor":false},{"index":4,"imageName":"M颈饰","isClear":true,"isColor":false,"isNew":1},{"index":5,"imageName":"M头发","isClear":true,"isColor":false,"isNew":1},{"index":6,"imageName":"M头饰","isClear":true,"isColor":false,"isNew":1},{"index":7,"imageName":"M尾巴","isClear":true,"isColor":false,"isNew":1},{"index":8,"imageName":"M眼睛","isClear":false,"isColor":false,"isNew":1},{"index":9,"imageName":"M衣服","isClear":true,"isColor":false,"isNew":1},{"index":10,"imageName":"M马蹄","isClear":true,"isColor":false,"isNew":1},{"index":11,"imageName":"M嘴巴","isClear":false,"isColor":false},{"index":12,"imageName":"M贴纸","isClear":true,"isColor":false}]]],0,0,[],[],[]]